flasc/__init__.py
flasc/flasc_dataframe.py
flasc/logging_manager.py
flasc/visualization.py
flasc/yaw_optimizer_visualization.py
flasc/analysis/__init__.py
flasc/analysis/analysis_input.py
flasc/analysis/energy_ratio.py
flasc/analysis/energy_ratio_heterogeneity_mapper.py
flasc/analysis/energy_ratio_input.py
flasc/analysis/energy_ratio_output.py
flasc/analysis/expected_power_analysis.py
flasc/analysis/expected_power_analysis_by.py
flasc/analysis/expected_power_analysis_output.py
flasc/analysis/expected_power_analysis_utilities.py
flasc/analysis/total_uplift_power_ratio.py
flasc/data_processing/__init__.py
flasc/data_processing/dataframe_manipulations.py
flasc/data_processing/energy_ratio_wd_bias_estimation.py
flasc/data_processing/filtering.py
flasc/data_processing/find_sensor_faults.py
flasc/data_processing/northing_offset.py
flasc/data_processing/northing_offset_change_hoger.py
flasc/data_processing/time_operations.py
flasc/model_fitting/__init__.py
flasc/model_fitting/cost_library.py
flasc/model_fitting/floris_sensitivity_analysis.py
flasc/model_fitting/floris_tuning.py
flasc/model_fitting/model_fit.py
flasc/model_fitting/opt_library.py
flasc/model_fitting/turbulence_estimator.py
flasc/model_fitting/yaw_pow_fitting.py
flasc/timing_tests/__init__.py
flasc/timing_tests/energy_ratio_timing.py
flasc/utilities/__init__.py
flasc/utilities/circular_statistics.py
flasc/utilities/energy_ratio_utilities.py
flasc/utilities/floris_tools.py
flasc/utilities/lookup_table_tools.py
flasc/utilities/optimization.py
flasc/utilities/tuner_utilities.py
flasc/utilities/utilities.py
flasc/utilities/utilities_examples.py
flasc-2.4.dist-info/licenses/AUTHORS.rst
flasc-2.4.dist-info/licenses/LICENSE.txt
flasc-2.4.dist-info/METADATA
flasc-2.4.dist-info/WHEEL
flasc-2.4.dist-info/top_level.txt
flasc-2.4.dist-info/RECORD
