Metadata-Version: 2.4
Name: flasc
Version: 2.4
Summary: FLASC provides a rich suite of analysis tools for SCADA data filtering & analysis, wind farm model validation, field experiment design, and field experiment monitoring.
Author-email: Paul Fleming <paul.fleming@nrel.gov>, "Michael (Misha) Sinner" <Michael.Sinner@nrel.gov>, Eric Simley <Eric.Simley@nrel.gov>
License: BSD 3-Clause License
Project-URL: Homepage, https://github.com/NREL/flasc
Project-URL: Documentation, https://readthedocs.org
Keywords: flasc
Classifier: Development Status :: 5 - Production/Stable
Classifier: Intended Audience :: Developers
Classifier: License :: OSI Approved :: BSD License
Classifier: Natural Language :: English
Classifier: Programming Language :: Python :: 3
Requires-Python: >=3.9
License-File: LICENSE.txt
License-File: AUTHORS.rst
Requires-Dist: bokeh<4,>=2
Requires-Dist: floris~=4.3
Requires-Dist: feather-format~=0.0
Requires-Dist: ipympl~=0.9
Requires-Dist: matplotlib~=3.8
Requires-Dist: numpy~=2.0
Requires-Dist: pandas~=2.0
Requires-Dist: SALib~=1.0
Requires-Dist: scipy~=1.1
Requires-Dist: streamlit~=1.0
Requires-Dist: tkcalendar~=1.0
Requires-Dist: seaborn~=0.0
Requires-Dist: polars~=1.0
Requires-Dist: ephem
Requires-Dist: coloredlogs~=15.0
Requires-Dist: res-wind-up~=0.1
Requires-Dist: optuna~=4.0
Requires-Dist: scikit-learn~=1.5
Provides-Extra: docs
Requires-Dist: jupyter-book; extra == "docs"
Requires-Dist: sphinx-book-theme; extra == "docs"
Requires-Dist: sphinx-autodoc-typehints; extra == "docs"
Requires-Dist: sphinxcontrib-autoyaml; extra == "docs"
Requires-Dist: sphinxcontrib.mermaid; extra == "docs"
Requires-Dist: numpydoc; extra == "docs"
Provides-Extra: develop
Requires-Dist: pytest; extra == "develop"
Requires-Dist: pre-commit; extra == "develop"
Requires-Dist: ruff; extra == "develop"
Requires-Dist: isort; extra == "develop"
Dynamic: license-file
